strawberry_django_phonenumber/__init__.py
strawberry_django_phonenumber/types/__init__.py
strawberry_django_phonenumber/types/phone_number.py
strawberry_django_phonenumber-0.2.0.dist-info/LICENSE.md
strawberry_django_phonenumber-0.2.0.dist-info/METADATA
strawberry_django_phonenumber-0.2.0.dist-info/WHEEL
strawberry_django_phonenumber-0.2.0.dist-info/RECORD
