Metadata-Version: 2.1
Name: strawberry-django-phonenumber
Version: 0.2.0
Summary: A strawberry + Django integration for phone numbers
Home-page: https://github.com/UpliftAgency/strawberry-django-phonenumber
License: MIT
Keywords: strawberry,django,phonenumber,phone,number,phonenumber-field,graphql,strawberry_django
Author: Paul Craciunoiu
Author-email: paul@craciunoiu.net
Requires-Python: >=3.10,<4
Classifier: License :: OSI Approved :: MIT License
Classifier: Programming Language :: Python :: 3
Classifier: Programming Language :: Python :: 3.10
Classifier: Programming Language :: Python :: 3.11
Classifier: Programming Language :: Python :: 3.12
Provides-Extra: psycopg
Provides-Extra: psycopg2
Requires-Dist: django (>=3)
Requires-Dist: django-phonenumber-field[phonenumberslite] (>=7)
Requires-Dist: psycopg2-binary ; extra == "psycopg2"
Requires-Dist: psycopg[binary] (>=3) ; extra == "psycopg"
Requires-Dist: strawberry-graphql-django (>=0.17)
Requires-Dist: strawberry-graphql[debug-server]
Project-URL: Repository, https://github.com/UpliftAgency/strawberry-django-phonenumber
